Metadata-Version: 2.1
Name: snoop-tensor
Version: 0.2
Summary: Tensor extension for snoop
Home-page: https://github.com/cmpute/snoop-tensor
Author: Jacob Zhong
Author-email: cmpute@gmail.com
License: UNKNOWN
Platform: UNKNOWN
